[{"copyright": "\u00a9 Google", "date": "2018-05", "location": {"lat": 39.6922552, "lng": -94.2294272}, "pano_id": "mPjo63Az1halrRX1_t0tzA", "status": "OK", "_file": "gsv_0.jpg"}, {"copyright": "\u00a9 Google", "date": "2018-05", "location": {"lat": 39.69234631568877, "lng": -94.22940411719644}, "pano_id": "KjcKHk3Z24LPKuRhh2U0dw", "status": "OK", "_file": "gsv_1.jpg"}, {"copyright": "\u00a9 Google", "date": "2018-05", "location": {"lat": 39.69243712423464, "lng": -94.22938111214118}, "pano_id": "_HAIYwklmu2aP-QAPr3tLw", "status": "OK", "_file": "gsv_2.jpg"}, {"copyright": "\u00a9 Google", "date": "2018-05", "location": {"lat": 39.69252807968284, "lng": -94.22935806980848}, "pano_id": "T1OgheamE4yeIoWjx32Wnw", "status": "OK", "_file": "gsv_3.jpg"}, {"copyright": "\u00a9 Google", "date": "2018-05", "location": {"lat": 39.69261920842573, "lng": -94.22933498351185}, "pano_id": "eT1DPim1RJsH3yu2csZzsA", "status": "OK", "_file": "gsv_4.jpg"}, {"copyright": "\u00a9 Google", "date": "2018-05", "location": {"lat": 39.69271042153553, "lng": -94.22931187577976}, "pano_id": "QGlzX6oYgsdo73e84KPsig", "status": "OK", "_file": "gsv_5.jpg"}, {"copyright": "\u00a9 Google", "date": "2018-05", "location": {"lat": 39.69280184614119, "lng": -94.22928871440531}, "pano_id": "7D8JX6SZiWmZG3dMHsHdBg", "status": "OK", "_file": "gsv_6.jpg"}, {"copyright": "\u00a9 Google", "date": "2018-05", "location": {"lat": 39.69289342209696, "lng": -94.22926551462538}, "pano_id": "QJ4whM1X9L0E9Kvw6QccAg", "status": "OK", "_file": "gsv_7.jpg"}, {"copyright": "\u00a9 Google", "date": "2018-05", "location": {"lat": 39.69298496625901, "lng": -94.22924232283737}, "pano_id": "0ouz8VtfyEIemkpROWis2A", "status": "OK", "_file": "gsv_8.jpg"}, {"copyright": "\u00a9 Google", "date": "2018-05", "location": {"lat": 39.69307663601717, "lng": -94.22921909916802}, "pano_id": "wbvLSB4dCcAKhbKNLjOBrA", "status": "OK", "_file": "gsv_9.jpg"}, {"copyright": "\u00a9 Google", "date": "2018-05", "location": {"lat": 39.69335165433336, "lng": -94.22914942549224}, "pano_id": "SOV1gz3rwgiQUfUKydSRrQ", "status": "OK", "_file": "gsv_10.jpg"}, {"copyright": "\u00a9 Google", "date": "2018-05", "location": {"lat": 39.69335165433336, "lng": -94.22914942549224}, "pano_id": "SOV1gz3rwgiQUfUKydSRrQ", "status": "OK", "_file": "gsv_11.jpg"}, {"copyright": "\u00a9 Google", "date": "2018-05", "location": {"lat": 39.6934431502442, "lng": -94.22912624561461}, "pano_id": "jlXYINuciMbcyDzyRbES-g", "status": "OK", "_file": "gsv_12.jpg"}, {"copyright": "\u00a9 Google", "date": "2018-05", "location": {"lat": 39.6935346499461, "lng": -94.2291030647139}, "pano_id": "fjH4-ZjR7tcP75ho0wqU1g", "status": "OK", "_file": "gsv_13.jpg"}, {"copyright": "\u00a9 Google", "date": "2018-05", "location": {"lat": 39.69362607188905, "lng": -94.22907990345043}, "pano_id": "n1i5hX_pL4BKukTLcxD0YA", "status": "OK", "_file": "gsv_14.jpg"}, {"copyright": "\u00a9 Google", "date": "2018-05", "location": {"lat": 39.69371725615581, "lng": -94.22905680233868}, "pano_id": "Udy_90eyd-0boVsPyVGYnw", "status": "OK", "_file": "gsv_15.jpg"}, {"copyright": "\u00a9 Google", "date": "2018-05", "location": {"lat": 39.69389964769663, "lng": -94.22901054959084}, "pano_id": "2gLb-VLMRrsEPPaql7CryA", "status": "OK", "_file": "gsv_16.jpg"}, {"copyright": "\u00a9 Google", "date": "2018-05", "location": {"lat": 39.69389964769663, "lng": -94.22901054959084}, "pano_id": "2gLb-VLMRrsEPPaql7CryA", "status": "OK", "_file": "gsv_17.jpg"}, {"copyright": "\u00a9 Google", "date": "2018-05", "location": {"lat": 39.69399120041265, "lng": -94.2289872403142}, "pano_id": "lVH6PQ9t8-_VG91Zlu3OMQ", "status": "OK", "_file": "gsv_18.jpg"}, {"copyright": "\u00a9 Google", "date": "2018-05", "location": {"lat": 39.69408279180772, "lng": -94.22896392112683}, "pano_id": "XzAPhrMWk2aqIHbJiQ-qxw", "status": "OK", "_file": "gsv_19.jpg"}, {"copyright": "\u00a9 Google", "date": "2018-05", "location": {"lat": 39.69426591900967, "lng": -94.22891729671574}, "pano_id": "EtWxGA9LpPGwMhabvvVsCw", "status": "OK", "_file": "gsv_20.jpg"}, {"copyright": "\u00a9 Google", "date": "2018-05", "location": {"lat": 39.69435759291691, "lng": -94.22889454433418}, "pano_id": "rIMKh8NBjt-pwZ_21NGcHQ", "status": "OK", "_file": "gsv_21.jpg"}, {"copyright": "\u00a9 Google", "date": "2018-05", "location": {"lat": 39.6944492096372, "lng": -94.22887205765163}, "pano_id": "IhZ4Bm3Tiv5cs97ggjBUtg", "status": "OK", "_file": "gsv_22.jpg"}, {"copyright": "\u00a9 Google", "date": "2018-05", "location": {"lat": 39.69454112979606, "lng": -94.22884949643117}, "pano_id": "64NJLLqj6akMHJ5UVCd6YQ", "status": "OK", "_file": "gsv_23.jpg"}, {"copyright": "\u00a9 Google", "date": "2018-05", "location": {"lat": 39.69463296936049, "lng": -94.228826954931}, "pano_id": "2sXTVJEGzj9OY6Pjte8znA", "status": "OK", "_file": "gsv_24.jpg"}, {"copyright": "\u00a9 Google", "date": "2018-05", "location": {"lat": 39.69472474019546, "lng": -94.2288044302391}, "pano_id": "n-xWpPFaC9uTYe0AoM5hFQ", "status": "OK", "_file": "gsv_25.jpg"}, {"copyright": "\u00a9 Google", "date": "2018-05", "location": {"lat": 39.69481603471574, "lng": -94.22878202239578}, "pano_id": "iuSZ1HjIG0FaNCt4ZJ92ew", "status": "OK", "_file": "gsv_26.jpg"}, {"copyright": "\u00a9 Google", "date": "2018-05", "location": {"lat": 39.69490731780134, "lng": -94.2287596172987}, "pano_id": "XhPNUfsSflKEfWsqwTvBiw", "status": "OK", "_file": "gsv_27.jpg"}, {"copyright": "\u00a9 Google", "date": "2018-05", "location": {"lat": 39.69499849238263, "lng": -94.22873723877343}, "pano_id": "rwDL60vi_RNlht46UV47Jw", "status": "OK", "_file": "gsv_28.jpg"}, {"copyright": "\u00a9 Google", "date": "2018-05", "location": {"lat": 39.69508998587832, "lng": -94.2287147819111}, "pano_id": "6B6eh0J5rnsh1dPSdh7iZA", "status": "OK", "_file": "gsv_29.jpg"}, {"copyright": "\u00a9 Google", "date": "2018-05", "location": {"lat": 39.69518149293734, "lng": -94.22869232165904}, "pano_id": "6Mwti4tTNHd1peC6Pa--Zg", "status": "OK", "_file": "gsv_30.jpg"}, {"copyright": "\u00a9 Google", "date": "2018-05", "location": {"lat": 39.69527292788273, "lng": -94.22866987904663}, "pano_id": "O_bFWsPPIXusza8JEABHdg", "status": "OK", "_file": "gsv_31.jpg"}, {"copyright": "\u00a9 Google", "date": "2018-05", "location": {"lat": 39.69536461028415, "lng": -94.22864737563563}, "pano_id": "W86Y2a62ZHck-Db5P78Pxg", "status": "OK", "_file": "gsv_32.jpg"}, {"copyright": "\u00a9 Google", "date": "2018-05", "location": {"lat": 39.69536461028415, "lng": -94.22864737563563}, "pano_id": "W86Y2a62ZHck-Db5P78Pxg", "status": "OK", "_file": "gsv_33.jpg"}, {"copyright": "\u00a9 Google", "date": "2018-05", "location": {"lat": 39.69545620985451, "lng": -94.2286241087765}, "pano_id": "eQUfuRB593fVmSJqrE8cKg", "status": "OK", "_file": "gsv_34.jpg"}, {"copyright": "\u00a9 Google", "date": "2018-05", "location": {"lat": 39.69554782005675, "lng": -94.2286007959073}, "pano_id": "P94OC38BKaPHM7B9Oskfhw", "status": "OK", "_file": "gsv_35.jpg"}, {"copyright": "\u00a9 Google", "date": "2018-05", "location": {"lat": 39.69563956476414, "lng": -94.22857744874615}, "pano_id": "Zw4b9Lb7cp66cwxNgBfhKg", "status": "OK", "_file": "gsv_36.jpg"}, {"copyright": "\u00a9 Google", "date": "2018-05", "location": {"lat": 39.69573147289138, "lng": -94.22855405993457}, "pano_id": "N1sEPRpoBv7qDwtBdp9SNw", "status": "OK", "_file": "gsv_37.jpg"}, {"copyright": "\u00a9 Google", "date": "2018-05", "location": {"lat": 39.69582336510497, "lng": -94.22853067510923}, "pano_id": "AxT_bHRITN-8iIJ0adOLCA", "status": "OK", "_file": "gsv_38.jpg"}, {"copyright": "\u00a9 Google", "date": "2018-05", "location": {"lat": 39.6959153418716, "lng": -94.22850726870318}, "pano_id": "cBJ52F5ABGtCP-YRoC6PWQ", "status": "OK", "_file": "gsv_39.jpg"}, {"copyright": "\u00a9 Google", "date": "2018-05", "location": {"lat": 39.69600739491437, "lng": -94.2284838428226}, "pano_id": "o9OCDaAy0Jeq0E-7WiJlZg", "status": "OK", "_file": "gsv_40.jpg"}, {"copyright": "\u00a9 Google", "date": "2018-05", "location": {"lat": 39.69609943939037, "lng": -94.22846041905845}, "pano_id": "cmWaEqPwLzgFMJCLSfbwnA", "status": "OK", "_file": "gsv_41.jpg"}, {"copyright": "\u00a9 Google", "date": "2018-05", "location": {"lat": 39.69619125628346, "lng": -94.22843705314686}, "pano_id": "rhKoEyJlr3dhrFAuqZKyAA", "status": "OK", "_file": "gsv_42.jpg"}, {"copyright": "\u00a9 Google", "date": "2018-05", "location": {"lat": 39.69628271489351, "lng": -94.22841377834952}, "pano_id": "kRvHD760mB2P9IhXOPzIwQ", "status": "OK", "_file": "gsv_43.jpg"}, {"copyright": "\u00a9 Google", "date": "2018-05", "location": {"lat": 39.6965518, "lng": -94.2283453}, "pano_id": "lYMRxx9jdZNdw7KeKZ-8pQ", "status": "OK", "_file": "gsv_44.jpg"}, {"copyright": "\u00a9 Google", "date": "2018-05", "location": {"lat": 39.6965518, "lng": -94.2283453}, "pano_id": "lYMRxx9jdZNdw7KeKZ-8pQ", "status": "OK", "_file": "gsv_45.jpg"}, {"copyright": "\u00a9 Google", "date": "2018-05", "location": {"lat": 39.69664611062413, "lng": -94.22832157587223}, "pano_id": "oOEz6fl14frSAmR4wy9ByQ", "status": "OK", "_file": "gsv_46.jpg"}, {"copyright": "\u00a9 Google", "date": "2018-05", "location": {"lat": 39.69673695127233, "lng": -94.22829872456515}, "pano_id": "2WnCu60LBWanI9Gzphm_hQ", "status": "OK", "_file": "gsv_47.jpg"}, {"copyright": "\u00a9 Google", "date": "2018-05", "location": {"lat": 39.69682681905939, "lng": -94.22827611792464}, "pano_id": "01yY4MBTZlIl4Pez1gRlng", "status": "OK", "_file": "gsv_48.jpg"}, {"copyright": "\u00a9 Google", "date": "2018-05", "location": {"lat": 39.69691766367609, "lng": -94.22825326549733}, "pano_id": "6OhFiattGIzaLY_yINbIbg", "status": "OK", "_file": "gsv_49.jpg"}, {"copyright": "\u00a9 Google", "date": "2018-05", "location": {"lat": 39.69700854621312, "lng": -94.22823040346967}, "pano_id": "HOSW1qMr7E4KuL17IgggOA", "status": "OK", "_file": "gsv_50.jpg"}, {"copyright": "\u00a9 Google", "date": "2018-05", "location": {"lat": 39.69709945620482, "lng": -94.22820753447425}, "pano_id": "a5GSCTXLio0AaosIBIr9qg", "status": "OK", "_file": "gsv_51.jpg"}, {"copyright": "\u00a9 Google", "date": "2018-05", "location": {"lat": 39.69719035000045, "lng": -94.22818466949172}, "pano_id": "vpnbjQu5Mw9PX3lkzQp-aQ", "status": "OK", "_file": "gsv_52.jpg"}, {"copyright": "\u00a9 Google", "date": "2018-05", "location": {"lat": 39.69728117538437, "lng": -94.22816182165734}, "pano_id": "900TGIF1d1fwuulqKofuZw", "status": "OK", "_file": "gsv_53.jpg"}, {"copyright": "\u00a9 Google", "date": "2018-05", "location": {"lat": 39.69737199966922, "lng": -94.2281389740382}, "pano_id": "xPd4rg7BacSCnAZpHPlPKg", "status": "OK", "_file": "gsv_54.jpg"}, {"copyright": "\u00a9 Google", "date": "2018-05", "location": {"lat": 39.69746280574403, "lng": -94.2281161309387}, "pano_id": "87gDOft3VBrklB2_AlPEOA", "status": "OK", "_file": "gsv_55.jpg"}, {"copyright": "\u00a9 Google", "date": "2018-05", "location": {"lat": 39.69755355946833, "lng": -94.22809330094728}, "pano_id": "Vpnq9oLfhJlFkMBclp-_3Q", "status": "OK", "_file": "gsv_56.jpg"}, {"copyright": "\u00a9 Google", "date": "2018-05", "location": {"lat": 39.69755355946833, "lng": -94.22809330094728}, "pano_id": "Vpnq9oLfhJlFkMBclp-_3Q", "status": "OK", "_file": "gsv_57.jpg"}, {"copyright": "\u00a9 Google", "date": "2018-05", "location": {"lat": 39.69764436984671, "lng": -94.22807045664274}, "pano_id": "LKL8G_NWQdpGvtDc6V4hrA", "status": "OK", "_file": "gsv_58.jpg"}, {"copyright": "\u00a9 Google", "date": "2018-05", "location": {"lat": 39.69773500411009, "lng": -94.22804765658073}, "pano_id": "OtJZG9_4kP3Nr-09xFPdBQ", "status": "OK", "_file": "gsv_59.jpg"}, {"copyright": "\u00a9 Google", "date": "2018-05", "location": {"lat": 39.6978255855508, "lng": -94.22802486974587}, "pano_id": "T9tD8bg2Ouu2ggBtSheZFA", "status": "OK", "_file": "gsv_60.jpg"}, {"copyright": "\u00a9 Google", "date": "2018-05", "location": {"lat": 39.69791605443304, "lng": -94.22800211116564}, "pano_id": "NnViX-73xWUcRrx8P1sa1g", "status": "OK", "_file": "gsv_61.jpg"}, {"copyright": "\u00a9 Google", "date": "2018-05", "location": {"lat": 39.69800644690745, "lng": -94.22797942937711}, "pano_id": "mnzEz0WZeyzLHm9FDr3C4A", "status": "OK", "_file": "gsv_62.jpg"}, {"copyright": "\u00a9 Google", "date": "2018-05", "location": {"lat": 39.69809680680675, "lng": -94.2279567870382}, "pano_id": "poHfIsPrJa1_-WllSzAYDA", "status": "OK", "_file": "gsv_63.jpg"}, {"copyright": "\u00a9 Google", "date": "2018-05", "location": {"lat": 39.69818632544565, "lng": -94.22793435508359}, "pano_id": "wfWGE_FZinQe0RceEHssgQ", "status": "OK", "_file": "gsv_64.jpg"}, {"copyright": "\u00a9 Google", "date": "2018-05", "location": {"lat": 39.69827463116626, "lng": -94.22791222733677}, "pano_id": "W_InZWcLUWrqe4DYWAzT5Q", "status": "OK", "_file": "gsv_65.jpg"}, {"copyright": "\u00a9 Google", "date": "2018-05", "location": {"lat": 39.69836293688687, "lng": -94.22789009958996}, "pano_id": "ew5egAta_X--FSBNVEbaCA", "status": "OK", "_file": "gsv_66.jpg"}, {"copyright": "\u00a9 Google", "date": "2018-05", "location": {"lat": 39.69845124260748, "lng": -94.22786797184312}, "pano_id": "DM4EnHWKkpsZJySL5Hko9g", "status": "OK", "_file": "gsv_67.jpg"}, {"copyright": "\u00a9 Google", "date": "2018-05", "location": {"lat": 39.69853954832809, "lng": -94.22784584409631}, "pano_id": "pplpfihcL3cccrpwLtkVjQ", "status": "OK", "_file": "gsv_68.jpg"}, {"copyright": "\u00a9 Google", "date": "2018-05", "location": {"lat": 39.69871680635085, "lng": -94.22780127527014}, "pano_id": "AD9BoANVtkcgj2ftAeJD8g", "status": "OK", "_file": "gsv_69.jpg"}, {"copyright": "\u00a9 Google", "date": "2018-05", "location": {"lat": 39.69880509660146, "lng": -94.22777904332025}, "pano_id": "COuRmnBD9utToTvmYbpI8Q", "status": "OK", "_file": "gsv_70.jpg"}, {"copyright": "\u00a9 Google", "date": "2018-05", "location": {"lat": 39.69889338685207, "lng": -94.22775681137036}, "pano_id": "GAnbBLj7YECVnLa54J6w5w", "status": "OK", "_file": "gsv_71.jpg"}, {"copyright": "\u00a9 Google", "date": "2018-05", "location": {"lat": 39.69898167710267, "lng": -94.22773457942046}, "pano_id": "1G2F3IJxjaLWbSz4H_9ufw", "status": "OK", "_file": "gsv_72.jpg"}, {"copyright": "\u00a9 Google", "date": "2018-05", "location": {"lat": 39.69898167710267, "lng": -94.22773457942046}, "pano_id": "1G2F3IJxjaLWbSz4H_9ufw", "status": "OK", "_file": "gsv_73.jpg"}, {"copyright": "\u00a9 Google", "date": "2018-05", "location": {"lat": 39.6990667190537, "lng": -94.2277136918937}, "pano_id": "RdafDbf_fo1Z0gVJHidYzQ", "status": "OK", "_file": "gsv_74.jpg"}, {"copyright": "\u00a9 Google", "date": "2018-05", "location": {"lat": 39.69915515716109, "lng": -94.22769247568105}, "pano_id": "xZwEDokJkqczwc7_Q3f0KA", "status": "OK", "_file": "gsv_75.jpg"}, {"copyright": "\u00a9 Google", "date": "2018-05", "location": {"lat": 39.69924359526848, "lng": -94.22767125946842}, "pano_id": "hxVifA1oHGfwP5-T-NeeDQ", "status": "OK", "_file": "gsv_76.jpg"}, {"copyright": "\u00a9 Google", "date": "2018-05", "location": {"lat": 39.69933203337588, "lng": -94.22765004325579}, "pano_id": "B4fQQ_YZVHvDBSSReYGVvQ", "status": "OK", "_file": "gsv_77.jpg"}, {"copyright": "\u00a9 Google", "date": "2018-05", "location": {"lat": 39.69933203337588, "lng": -94.22765004325579}, "pano_id": "B4fQQ_YZVHvDBSSReYGVvQ", "status": "OK", "_file": "gsv_78.jpg"}, {"copyright": "\u00a9 Google", "date": "2018-05", "location": {"lat": 39.69950890959067, "lng": -94.22760761083053}, "pano_id": "yUguLUTDCzl8K6zJP5BB1w", "status": "OK", "_file": "gsv_79.jpg"}, {"copyright": "\u00a9 Google", "date": "2018-05", "location": {"lat": 39.69959734769807, "lng": -94.2275863946179}, "pano_id": "vAXyWJ_aVr3YlnbnhLrOIw", "status": "OK", "_file": "gsv_80.jpg"}, {"copyright": "\u00a9 Google", "date": "2018-05", "location": {"lat": 39.69959734769807, "lng": -94.2275863946179}, "pano_id": "vAXyWJ_aVr3YlnbnhLrOIw", "status": "OK", "_file": "gsv_81.jpg"}, {"copyright": "\u00a9 Google", "date": "2018-05", "location": {"lat": 39.6997749, "lng": -94.2275438}, "pano_id": "LrBjbOT8bQewSFcnEiE1Zg", "status": "OK", "_file": "gsv_82.jpg"}, {"copyright": "\u00a9 Google", "date": "2018-05", "location": {"lat": 39.6997749, "lng": -94.2275438}, "pano_id": "LrBjbOT8bQewSFcnEiE1Zg", "status": "OK", "_file": "gsv_83.jpg"}, {"copyright": "\u00a9 Google", "date": "2018-05", "location": {"lat": 39.69987204282363, "lng": -94.22751950294032}, "pano_id": "Do2ZmrZYa6AjlRsR92lXIg", "status": "OK", "_file": "gsv_84.jpg"}, {"copyright": "\u00a9 Google", "date": "2018-05", "location": {"lat": 39.69996035448148, "lng": -94.22749741470426}, "pano_id": "-3C1O7kwt6aYVSxRWG9ouQ", "status": "OK", "_file": "gsv_85.jpg"}, {"copyright": "\u00a9 Google", "date": "2018-05", "location": {"lat": 39.7000574973051, "lng": -94.22747311764459}, "pano_id": "WwiDw1dzh-RDiuLFD7Lv3g", "status": "OK", "_file": "gsv_86.jpg"}, {"copyright": "\u00a9 Google", "date": "2018-05", "location": {"lat": 39.70014580896295, "lng": -94.22745102940853}, "pano_id": "D4aJtyPGduzIjtkkmE6hpQ", "status": "OK", "_file": "gsv_87.jpg"}, {"copyright": "\u00a9 Google", "date": "2018-05", "location": {"lat": 39.70014580896295, "lng": -94.22745102940853}, "pano_id": "D4aJtyPGduzIjtkkmE6hpQ", "status": "OK", "_file": "gsv_88.jpg"}, {"copyright": "\u00a9 Google", "date": "2018-05", "location": {"lat": 39.70023799331153, "lng": -94.2274277554745}, "pano_id": "FRgSevRnSuLD1ESPLhgFOw", "status": "OK", "_file": "gsv_89.jpg"}, {"copyright": "\u00a9 Google", "date": "2018-05", "location": {"lat": 39.7003350499182, "lng": -94.22740288302933}, "pano_id": "zc742tQFpFvAB1Z-mtEZiw", "status": "OK", "_file": "gsv_90.jpg"}, {"copyright": "\u00a9 Google", "date": "2018-05", "location": {"lat": 39.70042328319701, "lng": -94.22738027171553}, "pano_id": "5jvlu0fVOuMI3l3e0tb-lg", "status": "OK", "_file": "gsv_91.jpg"}, {"copyright": "\u00a9 Google", "date": "2018-05", "location": {"lat": 39.70060857308249, "lng": -94.22733278795657}, "pano_id": "-xZ9jBg6DAOldvSy0MeIXQ", "status": "OK", "_file": "gsv_92.jpg"}, {"copyright": "\u00a9 Google", "date": "2018-05", "location": {"lat": 39.70060857308249, "lng": -94.22733278795657}, "pano_id": "-xZ9jBg6DAOldvSy0MeIXQ", "status": "OK", "_file": "gsv_93.jpg"}, {"copyright": "\u00a9 Google", "date": "2018-05", "location": {"lat": 39.70070408756963, "lng": -94.22730831707715}, "pano_id": "27kEy8ZQKvxjpXQi0-_iaA", "status": "OK", "_file": "gsv_94.jpg"}, {"copyright": "\u00a9 Google", "date": "2018-05", "location": {"lat": 39.70079232203165, "lng": -94.22728571342358}, "pano_id": "qocNrC9mehzABxc7w_UaoQ", "status": "OK", "_file": "gsv_95.jpg"}, {"copyright": "\u00a9 Google", "date": "2018-05", "location": {"lat": 39.70088055649367, "lng": -94.22726310977004}, "pano_id": "Lwbbeq7vxYuRi8jZNUuRug", "status": "OK", "_file": "gsv_96.jpg"}, {"copyright": "\u00a9 Google", "date": "2018-05", "location": {"lat": 39.70096879095571, "lng": -94.22724050611647}, "pano_id": "t0ONEAs9GSkDKZOu7yNgBA", "status": "OK", "_file": "gsv_97.jpg"}, {"copyright": "\u00a9 Google", "date": "2018-05", "location": {"lat": 39.7010625, "lng": -94.2272165}, "pano_id": "7n6jKlxW7AICTMM6Y-17zA", "status": "OK", "_file": "gsv_98.jpg"}, {"copyright": "\u00a9 Google", "date": "2018-05", "location": {"lat": 39.70115075115628, "lng": -94.22719400655588}, "pano_id": "V6993QqccWO3NBDty9Ij5Q", "status": "OK", "_file": "gsv_99.jpg"}, {"copyright": "\u00a9 Google", "date": "2018-05", "location": {"lat": 39.70115075115628, "lng": -94.22719400655588}, "pano_id": "V6993QqccWO3NBDty9Ij5Q", "status": "OK", "_file": "gsv_100.jpg"}, {"copyright": "\u00a9 Google", "date": "2018-05", "location": {"lat": 39.70132725346885, "lng": -94.22714901966768}, "pano_id": "0DbZmivtGcsUklCckieDBA", "status": "OK", "_file": "gsv_101.jpg"}, {"copyright": "\u00a9 Google", "date": "2018-05", "location": {"lat": 39.70141550462512, "lng": -94.22712652622356}, "pano_id": "665hW_hOlV9zjOVDL60YcQ", "status": "OK", "_file": "gsv_102.jpg"}, {"copyright": "\u00a9 Google", "date": "2018-05", "location": {"lat": 39.7015037557814, "lng": -94.22710403277945}, "pano_id": "LrR1bOU0wSIxlK9CTMGUnQ", "status": "OK", "_file": "gsv_103.jpg"}, {"copyright": "\u00a9 Google", "date": "2018-05", "location": {"lat": 39.7015953, "lng": -94.2270807}, "pano_id": "gfHHRKOJvOKyCjOCKOZVAw", "status": "OK", "_file": "gsv_104.jpg"}, {"copyright": "\u00a9 Google", "date": "2018-05", "location": {"lat": 39.7015953, "lng": -94.2270807}, "pano_id": "gfHHRKOJvOKyCjOCKOZVAw", "status": "OK", "_file": "gsv_105.jpg"}, {"copyright": "\u00a9 Google", "date": "2018-05", "location": {"lat": 39.70168364100854, "lng": -94.22705881031402}, "pano_id": "GLxhJat0UhC5GOZ8xgefBA", "status": "OK", "_file": "gsv_106.jpg"}, {"copyright": "\u00a9 Google", "date": "2018-05", "location": {"lat": 39.70177198201708, "lng": -94.22703692062805}, "pano_id": "3drayym8PbzD_7btr7VEbg", "status": "OK", "_file": "gsv_107.jpg"}, {"copyright": "\u00a9 Google", "date": "2018-05", "location": {"lat": 39.70177198201708, "lng": -94.22703692062805}, "pano_id": "3drayym8PbzD_7btr7VEbg", "status": "OK", "_file": "gsv_108.jpg"}, {"copyright": "\u00a9 Google", "date": "2018-05", "location": {"lat": 39.70186915712647, "lng": -94.22701284197348}, "pano_id": "P-Op9mVBGgdgwym0C739cQ", "status": "OK", "_file": "gsv_109.jpg"}, {"copyright": "\u00a9 Google", "date": "2018-05", "location": {"lat": 39.70195749813502, "lng": -94.22699095228751}, "pano_id": "gvZcsuIdhaZAUSAFs9f7SQ", "status": "OK", "_file": "gsv_110.jpg"}, {"copyright": "\u00a9 Google", "date": "2018-05", "location": {"lat": 39.70204583914355, "lng": -94.22696906260154}, "pano_id": "5L7h69W6bElVOVtUGMolWA", "status": "OK", "_file": "gsv_111.jpg"}, {"copyright": "\u00a9 Google", "date": "2018-05", "location": {"lat": 39.70214301425295, "lng": -94.22694498394695}, "pano_id": "qfpAkpepMTAh26Lg01QE6g", "status": "OK", "_file": "gsv_112.jpg"}, {"copyright": "\u00a9 Google", "date": "2018-05", "location": {"lat": 39.702239, "lng": -94.2269212}, "pano_id": "OCiPp3Gmwb-aUo0I-m0u9Q", "status": "OK", "_file": "gsv_113.jpg"}, {"copyright": "\u00a9 Google", "date": "2018-05", "location": {"lat": 39.702239, "lng": -94.2269212}, "pano_id": "OCiPp3Gmwb-aUo0I-m0u9Q", "status": "OK", "_file": "gsv_114.jpg"}, {"copyright": "\u00a9 Google", "date": "2018-05", "location": {"lat": 39.70232746290767, "lng": -94.22690015825054}, "pano_id": "9Gf98TB_1qrOmhRxgOgzGQ", "status": "OK", "_file": "gsv_115.jpg"}, {"copyright": "\u00a9 Google", "date": "2018-05", "location": {"lat": 39.70241592581534, "lng": -94.2268791165011}, "pano_id": "hYY02EqE0YdQQ4ENYAbtkg", "status": "OK", "_file": "gsv_116.jpg"}, {"copyright": "\u00a9 Google", "date": "2018-05", "location": {"lat": 39.70250438872301, "lng": -94.22685807475162}, "pano_id": "pN4irMiP-vFAeDdBC1Mb2A", "status": "OK", "_file": "gsv_117.jpg"}, {"copyright": "\u00a9 Google", "date": "2018-05", "location": {"lat": 39.70250438872301, "lng": -94.22685807475162}, "pano_id": "pN4irMiP-vFAeDdBC1Mb2A", "status": "OK", "_file": "gsv_118.jpg"}, {"copyright": "\u00a9 Google", "date": "2018-05", "location": {"lat": 39.70259756036512, "lng": -94.22683504064682}, "pano_id": "Ylh-KhdE1Znxp6z3fCbDcQ", "status": "OK", "_file": "gsv_119.jpg"}, {"copyright": "\u00a9 Google", "date": "2018-05", "location": {"lat": 39.70259756036512, "lng": -94.22683504064682}, "pano_id": "Ylh-KhdE1Znxp6z3fCbDcQ", "status": "OK", "_file": "gsv_120.jpg"}, {"copyright": "\u00a9 Google", "date": "2018-05", "location": {"lat": 39.7026754, "lng": -94.2268146}, "pano_id": "9ETxd1mW7yog9VIuStIGhQ", "status": "OK", "_file": "gsv_121.jpg"}, {"copyright": "\u00a9 Google", "date": "2018-05", "location": {"lat": 39.70277259200645, "lng": -94.22679063651405}, "pano_id": "heJHnVH92-6JBCYpGyxa3Q", "status": "OK", "_file": "gsv_122.jpg"}, {"copyright": "\u00a9 Google", "date": "2018-05", "location": {"lat": 39.70286094837595, "lng": -94.22676885152683}, "pano_id": "AlG9tKxsDN8uDsrLvmRGWA", "status": "OK", "_file": "gsv_123.jpg"}, {"copyright": "\u00a9 Google", "date": "2018-05", "location": {"lat": 39.7029581403824, "lng": -94.22674488804088}, "pano_id": "jPLrf5LZ0PylzXRJOvVRpw", "status": "OK", "_file": "gsv_124.jpg"}, {"copyright": "\u00a9 Google", "date": "2018-05", "location": {"lat": 39.7029581403824, "lng": -94.22674488804088}, "pano_id": "jPLrf5LZ0PylzXRJOvVRpw", "status": "OK", "_file": "gsv_125.jpg"}, {"copyright": "\u00a9 Google", "date": "2018-05", "location": {"lat": 39.7029581403824, "lng": -94.22674488804088}, "pano_id": "jPLrf5LZ0PylzXRJOvVRpw", "status": "OK", "_file": "gsv_126.jpg"}, {"copyright": "\u00a9 Google", "date": "2018-05", "location": {"lat": 39.70304785658826, "lng": -94.2267216941388}, "pano_id": "aMzJPzmebHX501QdpUnzmg", "status": "OK", "_file": "gsv_127.jpg"}, {"copyright": "\u00a9 Google", "date": "2018-05", "location": {"lat": 39.70313595090204, "lng": -94.22669818437014}, "pano_id": "4w6oq39AGHJ-LZAsP5klRw", "status": "OK", "_file": "gsv_128.jpg"}, {"copyright": "\u00a9 Google", "date": "2018-05", "location": {"lat": 39.70322404521582, "lng": -94.22667467460147}, "pano_id": "GsqABtluqvrA7rabon9vew", "status": "OK", "_file": "gsv_129.jpg"}, {"copyright": "\u00a9 Google", "date": "2018-05", "location": {"lat": 39.70332094896096, "lng": -94.22664881385593}, "pano_id": "_93gxNhfeGCGffFS2pdl4Q", "status": "OK", "_file": "gsv_130.jpg"}, {"copyright": "\u00a9 Google", "date": "2018-05", "location": {"lat": 39.70341785270612, "lng": -94.22662295311041}, "pano_id": "ZQ66ZDlAFaYsO6GIcqa49A", "status": "OK", "_file": "gsv_131.jpg"}, {"copyright": "\u00a9 Google", "date": "2018-05", "location": {"lat": 39.70350838836069, "lng": -94.22659875245019}, "pano_id": "531DO6JNzoyAeJ5TUJrHkw", "status": "OK", "_file": "gsv_132.jpg"}, {"copyright": "\u00a9 Google", "date": "2018-05", "location": {"lat": 39.70359647672138, "lng": -94.22657520490037}, "pano_id": "1Xemz-S2b-rbi01ijIhVVw", "status": "OK", "_file": "gsv_133.jpg"}, {"copyright": "\u00a9 Google", "date": "2018-05", "location": {"lat": 39.70368456508207, "lng": -94.22655165735054}, "pano_id": "_c33YG7G5mf91dClBpP7Lg", "status": "OK", "_file": "gsv_134.jpg"}, {"copyright": "\u00a9 Google", "date": "2018-05", "location": {"lat": 39.70368456508207, "lng": -94.22655165735054}, "pano_id": "_c33YG7G5mf91dClBpP7Lg", "status": "OK", "_file": "gsv_135.jpg"}, {"copyright": "\u00a9 Google", "date": "2018-05", "location": {"lat": 39.70378206191234, "lng": -94.22652639642415}, "pano_id": "ostUoYZuVnm862uS8WETbw", "status": "OK", "_file": "gsv_136.jpg"}, {"copyright": "\u00a9 Google", "date": "2018-05", "location": {"lat": 39.70387038573703, "lng": -94.22650438927246}, "pano_id": "6nfmehg9X-84uF8HOpIPNQ", "status": "OK", "_file": "gsv_137.jpg"}, {"copyright": "\u00a9 Google", "date": "2018-05", "location": {"lat": 39.70396754194418, "lng": -94.22648018140559}, "pano_id": "JP5LfY0bMC1uX5yTQgHikQ", "status": "OK", "_file": "gsv_138.jpg"}, {"copyright": "\u00a9 Google", "date": "2018-05", "location": {"lat": 39.70406469815133, "lng": -94.22645597353872}, "pano_id": "EsZTYCPTsoPbHg711Bjubw", "status": "OK", "_file": "gsv_139.jpg"}, {"copyright": "\u00a9 Google", "date": "2018-05", "location": {"lat": 39.70406469815133, "lng": -94.22645597353872}, "pano_id": "EsZTYCPTsoPbHg711Bjubw", "status": "OK", "_file": "gsv_140.jpg"}, {"copyright": "\u00a9 Google", "date": "2018-05", "location": {"lat": 39.70415526892261, "lng": -94.22643302362204}, "pano_id": "GWQUwPA3hDJaJwSuflNTcw", "status": "OK", "_file": "gsv_141.jpg"}, {"copyright": "\u00a9 Google", "date": "2018-05", "location": {"lat": 39.7042435378452, "lng": -94.22641064724405}, "pano_id": "8ZlrRtwBclfSP2c0D9gGPA", "status": "OK", "_file": "gsv_142.jpg"}, {"copyright": "\u00a9 Google", "date": "2018-05", "location": {"lat": 39.70434063366006, "lng": -94.22638603322828}, "pano_id": "58h3Cgf0P8Z1Jw4nbonJNQ", "status": "OK", "_file": "gsv_143.jpg"}, {"copyright": "\u00a9 Google", "date": "2018-05", "location": {"lat": 39.70443772947491, "lng": -94.2263614192125}, "pano_id": "3j_fgBcyYxEHajXVxd1fLA", "status": "OK", "_file": "gsv_144.jpg"}, {"copyright": "\u00a9 Google", "date": "2018-05", "location": {"lat": 39.70453178462022, "lng": -94.22633757650898}, "pano_id": "bt6i1nTH08CbecQnNIJZ3Q", "status": "OK", "_file": "gsv_145.jpg"}, {"copyright": "\u00a9 Google", "date": "2018-05", "location": {"lat": 39.70462309421237, "lng": -94.22631442881875}, "pano_id": "8mPMz9CIAyapZ-lorhWSNA", "status": "OK", "_file": "gsv_146.jpg"}, {"copyright": "\u00a9 Google", "date": "2018-05", "location": {"lat": 39.70472019002722, "lng": -94.22628981480298}, "pano_id": "aA3CMISJc8T4zkD6PBJYTg", "status": "OK", "_file": "gsv_147.jpg"}, {"copyright": "\u00a9 Google", "date": "2018-05", "location": {"lat": 39.70472019002722, "lng": -94.22628981480298}, "pano_id": "aA3CMISJc8T4zkD6PBJYTg", "status": "OK", "_file": "gsv_148.jpg"}, {"copyright": "\u00a9 Google", "date": "2018-05", "location": {"lat": 39.70490488789143, "lng": -94.22624383138196}, "pano_id": "mtf4g3W3sMzHWzQCgIvVwA", "status": "OK", "_file": "gsv_149.jpg"}, {"copyright": "\u00a9 Google", "date": "2018-05", "location": {"lat": 39.70490488789143, "lng": -94.22624383138196}, "pano_id": "mtf4g3W3sMzHWzQCgIvVwA", "status": "OK", "_file": "gsv_150.jpg"}, {"copyright": "\u00a9 Google", "date": "2018-05", "location": {"lat": 39.70499327578286, "lng": -94.22622226276394}, "pano_id": "8syRevYnbBZrXdPqrDRN8Q", "status": "OK", "_file": "gsv_151.jpg"}, {"copyright": "\u00a9 Google", "date": "2018-05", "location": {"lat": 39.70527611703544, "lng": -94.22615324318622}, "pano_id": "BVQGbrVT9Td4_xihs8Frhg", "status": "OK", "_file": "gsv_152.jpg"}, {"copyright": "\u00a9 Google", "date": "2018-05", "location": {"lat": 39.70537334371601, "lng": -94.22612951770638}, "pano_id": "xo584oKFkqUTQ_cScuTLLw", "status": "OK", "_file": "gsv_153.jpg"}, {"copyright": "\u00a9 Google", "date": "2018-05", "location": {"lat": 39.70547057039658, "lng": -94.22610579222655}, "pano_id": "z6xds9KSQTyv2ae3e6IltQ", "status": "OK", "_file": "gsv_154.jpg"}, {"copyright": "\u00a9 Google", "date": "2018-05", "location": {"lat": 39.70556779707715, "lng": -94.22608206674671}, "pano_id": "2ziPBk90Lt-_HI0cQa5dqg", "status": "OK", "_file": "gsv_155.jpg"}, {"copyright": "\u00a9 Google", "date": "2018-05", "location": {"lat": 39.70565767382997, "lng": -94.2260600340507}, "pano_id": "lf7woBZb9xnid_O1AqtRrQ", "status": "OK", "_file": "gsv_156.jpg"}, {"copyright": "\u00a9 Google", "date": "2018-05", "location": {"lat": 39.70565767382997, "lng": -94.2260600340507}, "pano_id": "lf7woBZb9xnid_O1AqtRrQ", "status": "OK", "_file": "gsv_157.jpg"}, {"copyright": "\u00a9 Google", "date": "2018-05", "location": {"lat": 39.7058344214899, "lng": -94.2260167021521}, "pano_id": "CyAC45sXHRJ18ssrhK1LyQ", "status": "OK", "_file": "gsv_158.jpg"}, {"copyright": "\u00a9 Google", "date": "2018-05", "location": {"lat": 39.7058344214899, "lng": -94.2260167021521}, "pano_id": "CyAC45sXHRJ18ssrhK1LyQ", "status": "OK", "_file": "gsv_159.jpg"}, {"copyright": "\u00a9 Google", "date": "2018-05", "location": {"lat": 39.70592279531987, "lng": -94.22599503620282}, "pano_id": "FWCyQQP34Wyc0B_vOlKfnQ", "status": "OK", "_file": "gsv_160.jpg"}, {"copyright": "\u00a9 Google", "date": "2018-05", "location": {"lat": 39.70601116914984, "lng": -94.22597337025351}, "pano_id": "c8262XCj1cwlOgKro-U4Qw", "status": "OK", "_file": "gsv_161.jpg"}, {"copyright": "\u00a9 Google", "date": "2018-05", "location": {"lat": 39.7061016, "lng": -94.2259512}, "pano_id": "O6V_seHOhM3k4dXc6tQUrw", "status": "OK", "_file": "gsv_162.jpg"}, {"copyright": "\u00a9 Google", "date": "2018-05", "location": {"lat": 39.7061016, "lng": -94.2259512}, "pano_id": "O6V_seHOhM3k4dXc6tQUrw", "status": "OK", "_file": "gsv_163.jpg"}, {"copyright": "\u00a9 Google", "date": "2018-05", "location": {"lat": 39.70619870643996, "lng": -94.22592665621596}, "pano_id": "6ZxZn37Wwvay9zEugeN1IQ", "status": "OK", "_file": "gsv_164.jpg"}, {"copyright": "\u00a9 Google", "date": "2018-05", "location": {"lat": 39.70637526360355, "lng": -94.22588203115411}, "pano_id": "VKeEeLOnZCupU7HMXKH8JQ", "status": "OK", "_file": "gsv_165.jpg"}, {"copyright": "\u00a9 Google", "date": "2018-05", "location": {"lat": 39.70637526360355, "lng": -94.22588203115411}, "pano_id": "VKeEeLOnZCupU7HMXKH8JQ", "status": "OK", "_file": "gsv_166.jpg"}, {"copyright": "\u00a9 Google", "date": "2018-05", "location": {"lat": 39.70646354218534, "lng": -94.22585971862318}, "pano_id": "v5B8EUZmZPYf-J9Ug4s-Fw", "status": "OK", "_file": "gsv_167.jpg"}, {"copyright": "\u00a9 Google", "date": "2018-05", "location": {"lat": 39.70655182076713, "lng": -94.22583740609225}, "pano_id": "8glxh0vQCsFL8Ejr0lDz2w", "status": "OK", "_file": "gsv_168.jpg"}, {"copyright": "\u00a9 Google", "date": "2018-05", "location": {"lat": 39.7066377, "lng": -94.2258157}, "pano_id": "o9GTkFBSNLyg-POXRO8ODQ", "status": "OK", "_file": "gsv_169.jpg"}, {"copyright": "\u00a9 Google", "date": "2018-05", "location": {"lat": 39.70673478923264, "lng": -94.22579104127598}, "pano_id": "m4sKeXME3TPR2pYEwUxDtg", "status": "OK", "_file": "gsv_170.jpg"}, {"copyright": "\u00a9 Google", "date": "2018-05", "location": {"lat": 39.7068230521714, "lng": -94.22576862425413}, "pano_id": "XgiAUra4Kx-lrWPvds55lg", "status": "OK", "_file": "gsv_171.jpg"}, {"copyright": "\u00a9 Google", "date": "2018-05", "location": {"lat": 39.70691131511016, "lng": -94.2257462072323}, "pano_id": "UgArQuZ27Okr_-HF6hPicA", "status": "OK", "_file": "gsv_172.jpg"}, {"copyright": "\u00a9 Google", "date": "2018-05", "location": {"lat": 39.70699957804892, "lng": -94.22572379021045}, "pano_id": "9KhikdwBW_GAzBZZEvJ9_w", "status": "OK", "_file": "gsv_173.jpg"}, {"copyright": "\u00a9 Google", "date": "2018-05", "location": {"lat": 39.70708784098768, "lng": -94.22570137318861}, "pano_id": "t5CETbrdt4xjpUkXNFJaxw", "status": "OK", "_file": "gsv_174.jpg"}, {"copyright": "\u00a9 Google", "date": "2018-05", "location": {"lat": 39.7071779, "lng": -94.2256785}, "pano_id": "NV_99NVC3oxslMlVWXIECw", "status": "OK", "_file": "gsv_175.jpg"}, {"copyright": "\u00a9 Google", "date": "2018-05", "location": {"lat": 39.7071779, "lng": -94.2256785}, "pano_id": "NV_99NVC3oxslMlVWXIECw", "status": "OK", "_file": "gsv_176.jpg"}, {"copyright": "\u00a9 Google", "date": "2018-05", "location": {"lat": 39.70726617607107, "lng": -94.22565617037854}, "pano_id": "jVW3I10OTlv1ijG7nS6M0g", "status": "OK", "_file": "gsv_177.jpg"}, {"copyright": "\u00a9 Google", "date": "2018-05", "location": {"lat": 39.70736327974925, "lng": -94.22563160779494}, "pano_id": "hMj6NJwpV5SvbY-ltFuIgA", "status": "OK", "_file": "gsv_178.jpg"}, {"copyright": "\u00a9 Google", "date": "2018-05", "location": {"lat": 39.70745155582033, "lng": -94.22560927817348}, "pano_id": "6HPl-X7FMbtFIq3L9isVqg", "status": "OK", "_file": "gsv_179.jpg"}, {"copyright": "\u00a9 Google", "date": "2018-05", "location": {"lat": 39.70754388240432, "lng": -94.22558623569866}, "pano_id": "UHU8leJGdkpJbj8cAcxHBw", "status": "OK", "_file": "gsv_180.jpg"}, {"copyright": "\u00a9 Google", "date": "2018-05", "location": {"lat": 39.70754388240432, "lng": -94.22558623569866}, "pano_id": "UHU8leJGdkpJbj8cAcxHBw", "status": "OK", "_file": "gsv_181.jpg"}, {"copyright": "\u00a9 Google", "date": "2018-05", "location": {"lat": 39.707632247213, "lng": -94.22556450709597}, "pano_id": "8J2iX3zkota3SzuDhWL4tw", "status": "OK", "_file": "gsv_182.jpg"}, {"copyright": "\u00a9 Google", "date": "2018-05", "location": {"lat": 39.70772944850253, "lng": -94.22554060563301}, "pano_id": "55NjcIyod0Tiiemx4smRjQ", "status": "OK", "_file": "gsv_183.jpg"}, {"copyright": "\u00a9 Google", "date": "2018-05", "location": {"lat": 39.7078226, "lng": -94.2255177}, "pano_id": "QWutCEdAuKG0EpNQ-tj5Dg", "status": "OK", "_file": "gsv_184.jpg"}, {"copyright": "\u00a9 Google", "date": "2018-05", "location": {"lat": 39.70791098684876, "lng": -94.225496123292}, "pano_id": "4Il8ahn0Y1T2qkyFX_MQuQ", "status": "OK", "_file": "gsv_185.jpg"}, {"copyright": "\u00a9 Google", "date": "2018-05", "location": {"lat": 39.7080082123824, "lng": -94.22547238891323}, "pano_id": "NrZEAypLL-XsntA6sHjXaQ", "status": "OK", "_file": "gsv_186.jpg"}, {"copyright": "\u00a9 Google", "date": "2018-05", "location": {"lat": 39.70809659923116, "lng": -94.22545081220525}, "pano_id": "2CsXJzp7-k-Fd-9rB9n8_g", "status": "OK", "_file": "gsv_187.jpg"}, {"copyright": "\u00a9 Google", "date": "2018-05", "location": {"lat": 39.70818546731541, "lng": -94.22542893241483}, "pano_id": "aqu-0L5HHImIDB1ZHfvPRQ", "status": "OK", "_file": "gsv_188.jpg"}, {"copyright": "\u00a9 Google", "date": "2018-05", "location": {"lat": 39.70818546731541, "lng": -94.22542893241483}, "pano_id": "aqu-0L5HHImIDB1ZHfvPRQ", "status": "OK", "_file": "gsv_189.jpg"}, {"copyright": "\u00a9 Google", "date": "2018-05", "location": {"lat": 39.70828263540931, "lng": -94.22540480372749}, "pano_id": "3sErW2rtESHNqQZ2XoWWCA", "status": "OK", "_file": "gsv_190.jpg"}, {"copyright": "\u00a9 Google", "date": "2018-05", "location": {"lat": 39.70837980350321, "lng": -94.22538067504013}, "pano_id": "uAndFem7XZbOheyS7y_fvA", "status": "OK", "_file": "gsv_191.jpg"}, {"copyright": "\u00a9 Google", "date": "2018-05", "location": {"lat": 39.70847697159711, "lng": -94.22535654635277}, "pano_id": "aY9ZMCZfdRovxvswgiOInA", "status": "OK", "_file": "gsv_192.jpg"}, {"copyright": "\u00a9 Google", "date": "2018-05", "location": {"lat": 39.7085726, "lng": -94.2253328}, "pano_id": "WACLvmdzQin4_q-tldsbQQ", "status": "OK", "_file": "gsv_193.jpg"}, {"copyright": "\u00a9 Google", "date": "2018-05", "location": {"lat": 39.70866076122086, "lng": -94.22530971600345}, "pano_id": "I710OX-POhIEan_gC_j4eg", "status": "OK", "_file": "gsv_194.jpg"}, {"copyright": "\u00a9 Google", "date": "2018-05", "location": {"lat": 39.70874892244173, "lng": -94.2252866320069}, "pano_id": "KHMyHjaJRnKTZlyQVj82DA", "status": "OK", "_file": "gsv_195.jpg"}, {"copyright": "\u00a9 Google", "date": "2018-05", "location": {"lat": 39.70884094095562, "lng": -94.22526283804117}, "pano_id": "yhhda67Yl3fxRIj-ZMqP6w", "status": "OK", "_file": "gsv_196.jpg"}, {"copyright": "\u00a9 Google", "date": "2018-05", "location": {"lat": 39.70892917588166, "lng": -94.22524023477648}, "pano_id": "PWggsEWf_AKJEEzA9srXFg", "status": "OK", "_file": "gsv_197.jpg"}, {"copyright": "\u00a9 Google", "date": "2018-05", "location": {"lat": 39.7090262343003, "lng": -94.2252153711853}, "pano_id": "YIhLZc-W9nl_ldprW4j6aA", "status": "OK", "_file": "gsv_198.jpg"}, {"copyright": "\u00a9 Google", "date": "2018-05", "location": {"lat": 39.70911446922633, "lng": -94.2251927679206}, "pano_id": "sNKU1kM3E-qEYP9s1JMnoA", "status": "OK", "_file": "gsv_199.jpg"}, {"copyright": "\u00a9 Google", "date": "2018-05", "location": {"lat": 39.7092174, "lng": -94.2251664}, "pano_id": "7Mu3EZR4JYyBf4rA_pqq-A", "status": "OK", "_file": "gsv_200.jpg"}, {"copyright": "\u00a9 Google", "date": "2018-05", "location": {"lat": 39.7092174, "lng": -94.2251664}, "pano_id": "7Mu3EZR4JYyBf4rA_pqq-A", "status": "OK", "_file": "gsv_201.jpg"}, {"copyright": "\u00a9 Google", "date": "2018-05", "location": {"lat": 39.70929685632235, "lng": -94.22514635529477}, "pano_id": "np66wBUiFmQmpCS4RZ2T-w", "status": "OK", "_file": "gsv_202.jpg"}, {"copyright": "\u00a9 Google", "date": "2018-05", "location": {"lat": 39.70938514112496, "lng": -94.22512408340005}, "pano_id": "gfYXMxFXzJ0muKOXjA3TvA", "status": "OK", "_file": "gsv_203.jpg"}, {"copyright": "\u00a9 Google", "date": "2018-05", "location": {"lat": 39.7096463, "lng": -94.2250582}, "pano_id": "Yj-NKhx8o-BXJfFJqVCIig", "status": "OK", "_file": "gsv_204.jpg"}, {"copyright": "\u00a9 Google", "date": "2018-05", "location": {"lat": 39.70974343108463, "lng": -94.22503382030303}, "pano_id": "k8n7zsOyP2mwF8u6oPquJQ", "status": "OK", "_file": "gsv_205.jpg"}, {"copyright": "\u00a9 Google", "date": "2018-05", "location": {"lat": 39.70974343108463, "lng": -94.22503382030303}, "pano_id": "k8n7zsOyP2mwF8u6oPquJQ", "status": "OK", "_file": "gsv_206.jpg"}, {"copyright": "\u00a9 Google", "date": "2018-05", "location": {"lat": 39.70983173207064, "lng": -94.22501165694213}, "pano_id": "-LAcZRTTdb6X_nlIzzHx7g", "status": "OK", "_file": "gsv_207.jpg"}, {"copyright": "\u00a9 Google", "date": "2018-05", "location": {"lat": 39.70992886315526, "lng": -94.22498727724513}, "pano_id": "rM4VUop2UVbYPggSsIROnw", "status": "OK", "_file": "gsv_208.jpg"}, {"copyright": "\u00a9 Google", "date": "2018-05", "location": {"lat": 39.71001716414128, "lng": -94.22496511388424}, "pano_id": "kPC6N7bZhK6Ft7p3XcYIUw", "status": "OK", "_file": "gsv_209.jpg"}, {"copyright": "\u00a9 Google", "date": "2018-05", "location": {"lat": 39.71010748847377, "lng": -94.22494222234432}, "pano_id": "2JNy-b7YDcOsToHKUwKprw", "status": "OK", "_file": "gsv_210.jpg"}, {"copyright": "\u00a9 Google", "date": "2018-05", "location": {"lat": 39.71010748847377, "lng": -94.22494222234432}, "pano_id": "2JNy-b7YDcOsToHKUwKprw", "status": "OK", "_file": "gsv_211.jpg"}, {"copyright": "\u00a9 Google", "date": "2018-05", "location": {"lat": 39.71019570965822, "lng": -94.22491952820516}, "pano_id": "JLHPKfCG4bivVKHwhLq14Q", "status": "OK", "_file": "gsv_212.jpg"}, {"copyright": "\u00a9 Google", "date": "2018-05", "location": {"lat": 39.71029275296111, "lng": -94.22489456465208}, "pano_id": "nJYkJjyK4-fgIEWuRndguQ", "status": "OK", "_file": "gsv_213.jpg"}, {"copyright": "\u00a9 Google", "date": "2018-05", "location": {"lat": 39.71038097414555, "lng": -94.2248718705129}, "pano_id": "u_u2ipbH69pth1zh-kkVvQ", "status": "OK", "_file": "gsv_214.jpg"}, {"copyright": "\u00a9 Google", "date": "2018-05", "location": {"lat": 39.71046919533, "lng": -94.22484917637372}, "pano_id": "0jPq-GHcRK4kNzLuhAGMLA", "status": "OK", "_file": "gsv_215.jpg"}, {"copyright": "\u00a9 Google", "date": "2018-05", "location": {"lat": 39.71056015878656, "lng": -94.22482595585319}, "pano_id": "DqQI3EWI80e837F2JP2X9g", "status": "OK", "_file": "gsv_216.jpg"}]